ignis/__init__.py
ignis/__version__.py
ignis/aurum.py
ignis/corpus.py
ignis/probat.py
ignis/labeller/__init__.py
ignis/labeller/tomotopy.py
ignis/models/__init__.py
ignis/models/base.py
ignis/models/hdp.py
ignis/models/lda.py
ignis/tests/__init__.py
ignis/tests/test_corpus.py
ignis/tests/test_util.py
ignis/util/__init__.py
ignis/util/improved_phraser.py
ignis/util/jupyter_styles.py
ignis/util/lazy_loader.py
ignis/vis/__init__.py
ignis/vis/pyldavis.py
ignis_tm-1.5.0.dist-info/LICENCE
ignis_tm-1.5.0.dist-info/METADATA
ignis_tm-1.5.0.dist-info/WHEEL
ignis_tm-1.5.0.dist-info/top_level.txt
ignis_tm-1.5.0.dist-info/RECORD
