Metadata-Version: 2.1
Name: ignis-tm
Version: 1.5.0
Summary: Iterative topic modelling platform
Home-page: https://github.com/ZechyW/ignis-tm
Author: Zechy Wong
Author-email: zechywong@gmail.com
License: UNKNOWN
Project-URL: Bug Reports, https://github.com/ZechyW/ignis-tm/issues
Project-URL: Source, https://github.com/ZechyW/ignis-tm/
Keywords: analytics,nlp,topic modelling
Platform: UNKNOWN
Classifier: Development Status :: 4 - Beta
Classifier: Intended Audience :: Science/Research
Classifier: Topic :: Scientific/Engineering :: Information Analysis
Classifier: License :: OSI Approved :: MIT License
Classifier: Programming Language :: Python :: 3
Classifier: Programming Language :: Python :: 3.7
Classifier: Programming Language :: Python :: 3 :: Only
Requires-Python: >=3.7, <4
Requires-Dist: beautifulsoup4 (>=4.9.0)
Requires-Dist: gensim (>=4.0.0)
Requires-Dist: numpy (>=1.19.0)
Requires-Dist: pandas (>=1.0.3)
Requires-Dist: pyldavis (>=3.3.1)
Requires-Dist: tomotopy (>=0.10)
Requires-Dist: tqdm (>=4.46.0)
